posebutcher/__init__.py
posebutcher/butcher.py
posebutcher/o3d.py
posebutcher/vtk.py
posebutcher-0.0.22.dist-info/METADATA
posebutcher-0.0.22.dist-info/WHEEL
posebutcher-0.0.22.dist-info/RECORD
