Metadata-Version: 2.3
Name: PoseButcher
Version: 0.0.22
Summary: A tool for categorising and segmenting virtual hits with reference to experimental protein structures and (fragment) hits.
Project-URL: Homepage, https://github.com/mwinokan/PoseButcher
Project-URL: Bug Tracker, https://github.com/mwinokan/PoseButcher/issues
Author-email: Max Winokan <max@winokan.com>
Classifier: License :: OSI Approved :: MIT License
Classifier: Operating System :: OS Independent
Classifier: Programming Language :: Python :: 3
Requires-Python: >=3.9
Requires-Dist: ase
Requires-Dist: ipython
Requires-Dist: jupyterlab
Requires-Dist: molparse>=0.0.18
Requires-Dist: mpytools>=0.0.9
Requires-Dist: numpy
Requires-Dist: open3d>=0.18
Requires-Dist: pandas
Requires-Dist: py3dmol
Requires-Dist: pygamer
Requires-Dist: rdkit
